src/mk_elib/__about__.py
src/mk_elib/__init__.py
src/mk_elib/app.py
madskris_mk_elib-0.0.1.dist-info/METADATA
madskris_mk_elib-0.0.1.dist-info/WHEEL
madskris_mk_elib-0.0.1.dist-info/licenses/LICENSE.txt
madskris_mk_elib-0.0.1.dist-info/RECORD
